Metadata-Version: 2.1
Name: goclecdscraper
Version: 1.0.1
Summary: Scraper for Goclecd
Home-page: https://github.com/Harkame/GoclecdScraper
Author: Harkame
License: UNKNOWN
Platform: UNKNOWN
Classifier: Programming Language :: Python
Classifier: License :: OSI Approved
Classifier: Operating System :: OS Independent
Requires-Python: >=3.6
License-File: LICENSE
